Workbook

Sheet Guide
B1: Forwards Market-Making Simulator
B2: Pick any FX pair or commodity: the model prices its forward, quotes a two-way market with inventory skew, and hedges back-to-back when position or loss limits are breached.
B4: START HERE
B5: 1. Choose an instrument | C5: Inputs!C4 is a dropdown of 7 FX pairs, 5 commodities and one Custom row. Everything (pricing, quote size, spread, limits, labels, charts) re-prices when you change it.
B6: 2. Tweak assumptions | C6: Inputs shows each instrument's default, an optional Override column (blue on yellow) and the ACTIVE value the model uses. Leave Override blank to use the default.
B7: 3. Run a scenario | C7: On Simulation, edit the blue columns: market move (in step-vol units, so one scenario works for every instrument) and client action (BUY / SELL / NONE).
B8: 4. Read the results | C8: Summary: fills, hedges, P&L attribution, limit usage, checks and charts. Pricing: quote calculator and skew ladder for any inventory.
B9: SHEETS
B10: Inputs | C10: Instrument selector, defaults + overrides, global risk settings.
B11: Instruments | C11: The instrument library (one row each) with a live fair forward, forward points and premium/discount for every instrument. Edit a row or overwrite the Custom row to add your own.
B12: Pricing | C12: Step-by-step derivation of the fair forward for the selected instrument, a live quote calculator and a skew ladder.
B13: Simulation | C13: 60-step market replay: market move, client RFQ, quotes, fill, P&L, limit checks and hedge for every step.
B14: Summary | C14: Fills, hedges, P&L attribution (spread capture / mark-to-market / hedge cost), limit usage, checks, charts.
B15: PRICING
B16: One formula, two readings | C16: F = Spot x (1 + rate B x d / basis B) / (1 + rate A x d / basis A).
B17: FX pair BASE/QUOTE | C17: Covered interest parity: rate A = BASE-currency rate, rate B = QUOTE-currency rate. Higher-yielding currency trades at a forward discount. Position unit = BASE currency; P&L in QUOTE currency.
B18: Commodity | C18: Cost of carry: rate A = convenience yield, rate B = financing + storage cost. Carry > yield gives contango (forward above spot, e.g. Gold, Natural Gas); yield > carry gives backwardation (e.g. WTI). P&L in USD.
B19: QUOTING AND RISK
B20: Quotes | C20: Mid = fair forward + skew. Bid = round(fair/tick + skew - spread/2) x tick, Ask = Bid + spread. Fixed clip size each side.
B21: Skew | C21: Skew (ticks) = -(position / position limit, capped at +/-100%) x max skew. Long inventory pushes both quotes down (cheap to buy from us, unattractive to sell to us); short pushes them up.
B22: Position limit | C22: If |position| after a client fill exceeds the limit, a back-to-back hedge trades the street back to the residual (% of limit, default 0 = flat), paying the street half-spread.
B23: Loss limit | C23: If cumulative P&L (before that step's hedge cost) reaches -loss limit, the book is flattened. With 'halt' = 1 quoting then stops for the rest of the run.
B24: CONVENTIONS
B25: Position | C25: Net units bought forward from clients (+ = long). Client BUY lifts our Ask (we go shorter); client SELL hits our Bid.
B26: P&L | C26: In the quote/P&L currency, measured against fair forward: spread capture + mark-to-market of opening position on the fair-forward move + street hedge cost.
B27: Market move | C27: Spot change per step = move (sigma units) x step vol (ticks) x tick. Step vol is set per instrument.
B28: LIMITATIONS
B29: Simplifications | C29: Constant tenor each step (no roll-down); P&L not discounted; one RFQ per step at a fixed size; hedges fill instantly at fair +/- street half-spread. ALL spots, rates, sizes and limits are illustrative placeholders, not live market data: update them before drawing conclusions. The default scenario is randomly generated (seed 277) for demonstration.

Sheet Inputs
B1: Inputs & Assumptions
B2: Blue on yellow = editable. Pick an instrument; leave Override blank to use its default. The ACTIVE column (bold) is what the model uses.
B4: Select instrument (FX pair or commodity) | C4: USD/SGD | D4: <- dropdown; change me
B5: Row in Instruments table | C5: =MATCH(Instrument,Instruments!$B$6:$B$18,0) -> 1
B6: Instrument note | C6: =INDEX(Instruments!$Y$6:$Y$18,Inst_Row) -> Original project brief: USD 4.00%, SGD 0.55%, 45-day tenor, USD 250k, 5-tick spread. Spot illustrative.
B8: Assumption | C8: Instrument default | D8: Override (optional) | E8: ACTIVE value | F8: Unit | G8: Note
B9: INSTRUMENT
B10: Instrument type | C10: =INDEX(Instruments!$C$6:$C$18,Inst_Row) -> FX | D10: - | E10: =C10 -> FX | G10: FX = interest-rate parity; Commodity = cost of carry.
B11: Position unit | C11: =INDEX(Instruments!$D$6:$D$18,Inst_Row) -> USD | D11: - | E11: =C11 -> USD | G11: FX: base currency. Commodity: contract unit (oz, bbl, t, MMBtu).
B12: P&L / quote currency | C12: =INDEX(Instruments!$E$6:$E$18,Inst_Row) -> SGD | D12: - | E12: =C12 -> SGD | G12: All P&L, loss limit and hedge cost are in this currency.
B13: PRICING
B14: Starting spot price | C14: =INDEX(Instruments!$F$6:$F$18,Inst_Row) -> 1.285 | E14: =IF(D14="",C14,D14) -> 1.285 | F14: =PnL_Ccy&" per "&Unit_Label -> SGD per USD | G14: Illustrative level, not live market data.
B15: =IF(Inst_Type="FX","Rate A: base-currency interest rate","Rate A: convenience yield") -> Rate A: base-currency interest rate | C15: =INDEX(Instruments!$G$6:$G$18,Inst_Row) -> 0.04 | E15: =IF(D15="",C15,D15) -> 0.04 | F15: % p.a. | G15: Denominator of the forward formula. USD/SGD brief: USD 4.00%.
B16: =IF(Inst_Type="FX","Rate B: quote-currency interest rate","Rate B: financing + storage cost") -> Rate B: quote-currency interest rate | C16: =INDEX(Instruments!$J$6:$J$18,Inst_Row) -> 0.0055 | E16: =IF(D16="",C16,D16) -> 0.0055 | F16: % p.a. | G16: Numerator of the forward formula. USD/SGD brief: SGD 0.55%. Commodity: financing + storage.
B17: Day-count basis for rate A | C17: =INDEX(Instruments!$K$6:$K$18,Inst_Row) -> 360 | E17: =IF(D17="",C17,D17) -> 360 | F17: days | G17: Money-market convention: ACT/360 for USD, EUR, JPY, CHF; ACT/365 for GBP, AUD, SGD, CNH.
B18: Day-count basis for rate B | C18: =INDEX(Instruments!$L$6:$L$18,Inst_Row) -> 365 | E18: =IF(D18="",C18,D18) -> 365 | F18: days
B19: Forward tenor | C19: =INDEX(Instruments!$M$6:$M$18,Inst_Row) -> 45 | E19: =IF(D19="",C19,D19) -> 45 | F19: days | G19: USD/SGD brief: 45 days.
B20: QUOTING
B21: Tick size | C21: =INDEX(Instruments!$N$6:$N$18,Inst_Row) -> 0.0001 | E21: =IF(D21="",C21,D21) -> 0.0001 | F21: =PnL_Ccy&" per "&Unit_Label -> SGD per USD | G21: 1 tick = smallest quoted price increment.
B22: Quote size per side | C22: =INDEX(Instruments!$O$6:$O$18,Inst_Row) -> 250000 | E22: =IF(D22="",C22,D22) -> 250000 | F22: =Unit_Label -> USD | G22: USD/SGD brief: USD 250k per side.
B23: Bid/offer spread | C23: =INDEX(Instruments!$P$6:$P$18,Inst_Row) -> 5 | E23: =IF(D23="",C23,D23) -> 5 | F23: ticks | G23: USD/SGD brief: 5 ticks.
B24: Max skew at full position limit | C24: =INDEX(Instruments!$Q$6:$Q$18,Inst_Row) -> 3 | E24: =IF(D24="",C24,D24) -> 3 | F24: ticks | G24: How hard quotes lean away from inventory at limit; linear below.
B25: RISK LIMITS & HEDGING
B26: Position limit (absolute) | C26: =INDEX(Instruments!$R$6:$R$18,Inst_Row) -> 1000000 | E26: =IF(D26="",C26,D26) -> 1000000 | F26: =Unit_Label -> USD | G26: Breach -> back-to-back hedge with the street.
B27: Cumulative loss limit | C27: =INDEX(Instruments!$S$6:$S$18,Inst_Row) -> 1800 | E27: =IF(D27="",C27,D27) -> 1800 | F27: =PnL_Ccy -> SGD | G27: Breach -> flatten the book with the street.
B28: Street half-spread paid on hedges | C28: =INDEX(Instruments!$T$6:$T$18,Inst_Row) -> 1 | E28: =IF(D28="",C28,D28) -> 1 | F28: ticks | G28: Hedges execute at fair forward -/+ this many ticks.
B29: Residual position after limit hedge (% of position limit) | C29: - | D29: - | E29: 0 | F29: % of limit | G29: 0% = hedge fully flat; 25% keeps a quarter-limit residual in the same direction. Assumption.
B30: = residual position | C30: - | D30: - | E30: =Hedge_Target_Pct*Pos_Limit -> 0 | F30: =Unit_Label -> USD
B31: Halt quoting after loss-limit breach (1 = yes, 0 = no) | C31: - | D31: - | E31: 1 | F31: flag | G31: 0 = keep quoting (the desk re-flattens every step cumulative P&L stays below the limit). Assumption.
B32: SIMULATION
B33: Step volatility (1.0 sigma move per step) | C33: =INDEX(Instruments!$U$6:$U$18,Inst_Row) -> 3 | E33: =IF(D33="",C33,D33) -> 3 | F33: ticks | G33: Simulation market moves are in sigma units x this x tick.
B34: Opening position | C34: - | D34: - | E34: 0 | F34: =Unit_Label -> USD | G34: Assumption: start flat.

Sheet Instruments
B1: Instrument Library
B2: One row per instrument. Blue = editable input; black = formula. Spots, rates, sizes and limits are ILLUSTRATIVE placeholders, not live market data. Overwrite the Custom row (yellow) to add your own.
B3: Rate A / Rate B: FX = base / quote currency interest rate; Commodity = convenience yield / (financing + storage cost). Loss limit default = 6 x position limit x step vol x tick.
B5: Instrument | C5: Type | D5: Position unit | E5: P&L ccy | F5: Spot | G5: Rate A | H5: Financing (commodity) | I5: Storage (commodity) | J5: Rate B | K5: Day basis A | L5: Day basis B | M5: Tenor (days) | N5: Tick size | O5: Quote size (units) | P5: Spread (ticks) | Q5: Max skew (ticks) | R5: Position limit (units) | S5: Loss limit (P&L ccy) | T5: Hedge cost (ticks) | U5: Step vol (ticks) | V5: Fair forward | W5: Fwd points (ticks) | X5: Premium / (discount) p.a. | Y5: Source / note
B6: USD/SGD | C6: FX | D6: USD | E6: SGD | F6: 1.285 | G6: 0.04 | H6: n/a | I6: n/a | J6: 0.0055 | K6: 360 | L6: 365 | M6: 45 | N6: 0.0001 | O6: 250000 | P6: 5 | Q6: 3 | R6: 1000000 | S6: 1800 | T6: 1 | U6: 3 | V6: =F6*(1+J6*M6/L6)/(1+G6*M6/K6) -> 1.279474 | W6: =(V6-F6)/N6 -> -55.260342 | X6: =(V6/F6-1)*365/M6 -> -0.03488115 | Y6: Original project brief: USD 4.00%, SGD 0.55%, 45-day tenor, USD 250k, 5-tick spread. Spot illustrative.
B7: EUR/USD | C7: FX | D7: EUR | E7: USD | F7: 1.16 | G7: 0.02 | H7: n/a | I7: n/a | J7: 0.04 | K7: 360 | L7: 360 | M7: 45 | N7: 0.0001 | O7: 250000 | P7: 2 | Q7: 1 | R7: 1000000 | S7: 2400 | T7: 0.5 | U7: 4 | V7: =F7*(1+J7*M7/L7)/(1+G7*M7/K7) -> 1.1628928 | W7: =(V7-F7)/N7 -> 28.927681 | X7: =(V7/F7-1)*365/M7 -> 0.02022721 | Y7: Most liquid pair: tight spread. Rates illustrative (EUR 2.00%, USD 4.00%).
B8: GBP/USD | C8: FX | D8: GBP | E8: USD | F8: 1.34 | G8: 0.04 | H8: n/a | I8: n/a | J8: 0.04 | K8: 365 | L8: 360 | M8: 45 | N8: 0.0001 | O8: 250000 | P8: 3 | Q8: 2 | R8: 1000000 | S8: 3000 | T8: 1 | U8: 5 | V8: =F8*(1+J8*M8/L8)/(1+G8*M8/K8) -> 1.3400913 | W8: =(V8-F8)/N8 -> 0.91330425 | X8: =(V8/F8-1)*365/M8 -> 0.00055282927 | Y8: Rates illustrative (GBP 4.00%, USD 4.00%): near-zero carry, forward ~ spot.
B9: USD/JPY | C9: FX | D9: USD | E9: JPY | F9: 150 | G9: 0.04 | H9: n/a | I9: n/a | J9: 0.005 | K9: 360 | L9: 360 | M9: 45 | N9: 0.01 | O9: 250000 | P9: 3 | Q9: 2 | R9: 1000000 | S9: 360000 | T9: 1 | U9: 6 | V9: =F9*(1+J9*M9/L9)/(1+G9*M9/K9) -> 149.34701 | W9: =(V9-F9)/N9 -> -65.298507 | X9: =(V9/F9-1)*365/M9 -> -0.035309563 | Y9: JPY quoted to 2 decimals (1 tick = 0.01). Large forward discount: USD yield >> JPY yield. Illustrative.
B10: AUD/USD | C10: FX | D10: AUD | E10: USD | F10: 0.66 | G10: 0.036 | H10: n/a | I10: n/a | J10: 0.04 | K10: 365 | L10: 360 | M10: 45 | N10: 0.0001 | O10: 250000 | P10: 3 | Q10: 2 | R10: 1000000 | S10: 2400 | T10: 1 | U10: 4 | V10: =F10*(1+J10*M10/L10)/(1+G10*M10/K10) -> 0.66036905 | W10: =(V10-F10)/N10 -> 3.6904697 | X10: =(V10/F10-1)*365/M10 -> 0.0045354257 | Y10: Rates illustrative (AUD 3.60%, USD 4.00%).
B11: USD/CHF | C11: FX | D11: USD | E11: CHF | F11: 0.8 | G11: 0.04 | H11: n/a | I11: n/a | J11: 0.0025 | K11: 360 | L11: 360 | M11: 45 | N11: 0.0001 | O11: 250000 | P11: 3 | Q11: 2 | R11: 1000000 | S11: 2400 | T11: 1 | U11: 4 | V11: =F11*(1+J11*M11/L11)/(1+G11*M11/K11) -> 0.79626866 | W11: =(V11-F11)/N11 -> -37.313433 | X11: =(V11/F11-1)*365/M11 -> -0.037831675 | Y11: Rates illustrative (USD 4.00%, CHF 0.25%): large forward discount.
B12: USD/CNH | C12: FX | D12: USD | E12: CNH | F12: 7.15 | G12: 0.04 | H12: n/a | I12: n/a | J12: 0.018 | K12: 360 | L12: 365 | M12: 45 | N12: 0.0001 | O12: 250000 | P12: 8 | Q12: 4 | R12: 1000000 | S12: 3000 | T12: 1 | U12: 5 | V12: =F12*(1+J12*M12/L12)/(1+G12*M12/K12) -> 7.130216 | W12: =(V12-F12)/N12 -> -197.83957 | X12: =(V12/F12-1)*365/M12 -> -0.022443339 | Y12: Offshore yuan: wider spread / skew than G10. Rates illustrative (USD 4.00%, CNH 1.80%).
B13: Gold | C13: Commodity | D13: oz | E13: USD | F13: 4000 | G13: 0.002 | H13: 0.04 | I13: 0.001 | J13: =H13+I13 -> 0.041 | K13: 365 | L13: 365 | M13: 90 | N13: 0.1 | O13: 1000 | P13: 5 | Q13: 3 | R13: 4000 | S13: 36000 | T13: 1 | U13: 15 | V13: =F13*(1+J13*M13/L13)/(1+G13*M13/K13) -> 4038.4468 | W13: =(V13-F13)/N13 -> 384.46793 | X13: =(V13/F13-1)*365/M13 -> 0.038980777 | Y13: Price USD/oz, 90-day forward. Conv. yield ~ lease rate 0.20%; financing 4.00% + storage 0.10%. Contango. Illustrative.
B14: Silver | C14: Commodity | D14: oz | E14: USD | F14: 45 | G14: 0.003 | H14: 0.04 | I14: 0.003 | J14: =H14+I14 -> 0.043 | K14: 365 | L14: 365 | M14: 90 | N14: 0.01 | O14: 50000 | P14: 5 | Q14: 3 | R14: 200000 | S14: 120000 | T14: 1 | U14: 10 | V14: =F14*(1+J14*M14/L14)/(1+G14*M14/K14) -> 45.443508 | W14: =(V14-F14)/N14 -> 44.350754 | X14: =(V14/F14-1)*365/M14 -> 0.039970433 | Y14: Price USD/oz, 90-day forward. Conv. yield 0.30%; financing 4.00% + storage 0.30%. Illustrative.
B15: WTI Crude | C15: Commodity | D15: bbl | E15: USD | F15: 65 | G15: 0.07 | H15: 0.04 | I15: 0.02 | J15: =H15+I15 -> 0.06 | K15: 365 | L15: 365 | M15: 90 | N15: 0.01 | O15: 10000 | P15: 4 | Q15: 3 | R15: 40000 | S15: 19200 | T15: 1 | U15: 8 | V15: =F15*(1+J15*M15/L15)/(1+G15*M15/K15) -> 64.842445 | W15: =(V15-F15)/N15 -> -15.755454 | X15: =(V15/F15-1)*365/M15 -> -0.0098303259 | Y15: Price USD/bbl, 90-day forward. Conv. yield 7.00% > carry 6.00% -> mild BACKWARDATION (forward < spot). Illustrative.
B16: Copper | C16: Commodity | D16: t | E16: USD | F16: 10000 | G16: 0.02 | H16: 0.04 | I16: 0.01 | J16: =H16+I16 -> 0.05 | K16: 365 | L16: 365 | M16: 90 | N16: 0.5 | O16: 25 | P16: 4 | Q16: 2 | R16: 100 | S16: 3000 | T16: 1 | U16: 10 | V16: =F16*(1+J16*M16/L16)/(1+G16*M16/K16) -> 10073.61 | W16: =(V16-F16)/N16 -> 147.21919 | X16: =(V16/F16-1)*365/M16 -> 0.029852781 | Y16: Price USD/tonne, 90-day forward. Conv. yield 2.00%; financing 4.00% + storage 1.00%. Illustrative.
B17: Natural Gas | C17: Commodity | D17: MMBtu | E17: USD | F17: 3.5 | G17: 0 | H17: 0.04 | I17: 0.12 | J17: =H17+I17 -> 0.16 | K17: 365 | L17: 365 | M17: 90 | N17: 0.001 | O17: 10000 | P17: 5 | Q17: 3 | R17: 40000 | S17: 2400 | T17: 1 | U17: 10 | V17: =F17*(1+J17*M17/L17)/(1+G17*M17/K17) -> 3.6380822 | W17: =(V17-F17)/N17 -> 138.08219 | X17: =(V17/F17-1)*365/M17 -> 0.16 | Y17: Price USD/MMBtu, 90-day forward. Very high storage cost (12%) -> steep CONTANGO. Illustrative.
B18: Custom (edit me) | C18: FX | D18: USD | E18: MYR | F18: 4.2 | G18: 0.04 | H18: n/a | I18: n/a | J18: 0.03 | K18: 360 | L18: 365 | M18: 45 | N18: 0.0001 | O18: 250000 | P18: 8 | Q18: 4 | R18: 1000000 | S18: 3000 | T18: 1 | U18: 5 | V18: =F18*(1+J18*M18/L18)/(1+G18*M18/K18) -> 4.1945614 | W18: =(V18-F18)/N18 -> -54.385606 | X18: =(V18/F18-1)*365/M18 -> -0.01050304 | Y18: EXAMPLE ROW (USD/MYR, illustrative): overwrite every blue cell with your own instrument.
B20: Highlighted row = instrument currently selected on Inputs.

Sheet Pricing
B1: ="Pricing: "&Instrument&" ("&Inst_Type&")" -> Pricing: USD/SGD (FX)
B2: Fair forward from interest-rate parity (FX) or cost of carry (commodity), then the skewed two-way quote for any inventory.
B4: 1. Fair forward
B5: ="Spot ("&PnL_Ccy&" per "&Unit_Label&")" -> Spot (SGD per USD) | C5: =Spot_Init -> 1.285
B6: =IF(Inst_Type="FX","Rate-A factor 1 + r_base x d / basis","Convenience-yield factor 1 + y x d / basis") -> Rate-A factor 1 + r_base x d / basis | C6: =1+Rate_A*Tenor_Days/Basis_A -> 1.005
B7: =IF(Inst_Type="FX","Rate-B factor 1 + r_quote x d / basis","Carry factor 1 + (financing + storage) x d / basis") -> Rate-B factor 1 + r_quote x d / basis | C7: =1+Rate_B*Tenor_Days/Basis_B -> 1.0006781
B8: Fair forward outright = Spot x B-factor / A-factor | C8: =C5*C7/C6 -> 1.279474 | D8: =IF(C8<C5,"Forward at a DISCOUNT to spot"&IF(Inst_Type="FX"," (base-ccy yield > quote-ccy yield)"," (backwardation: yield > carry)"),"Forward at a PREMIUM to spot"&IF(Inst_Type="FX"," (quote-ccy yield > base-ccy yield)"," (contango: carry > yield)")) -> Forward at a DISCOUNT to spot (base-ccy yield > quote-ccy yield)
B9: Forward points (ticks) | C9: =(C8-C5)/Tick -> -55.260342
B10: Forward premium / (discount) p.a. | C10: =(C8/C5-1)*365/Tenor_Days -> -0.03488115
B11: Rate differential (B - A) | C11: =Rate_B-Rate_A -> -0.0345
B13: 2. Live quote calculator
B14: Current position, in clips (edit me; + = long) | C14: 2
B15: ="Current position ("&Unit_Label&")" -> Current position (USD) | C15: =C14*Clip_Size -> 500000
B16: Position utilisation of limit | C16: =C15/Pos_Limit -> 0.5
B17: Skew (ticks) | C17: =-MAX(-1,MIN(1,C16))*Max_Skew_Ticks -> -1.5
B18: Bid (client sells to us) | C18: =ROUND(C8/Tick+C17-Spread_Ticks/2,0)*Tick -> 1.2791
B19: Ask (client buys from us) | C19: =C18+Spread_Ticks*Tick -> 1.2796
B20: Quoted spread (ticks) | C20: =(C19-C18)/Tick -> 5
B21: Mid vs fair forward (ticks) | C21: =((C18+C19)/2-C8)/Tick -> -1.2396579
B22: ="Quote size each side ("&Unit_Label&")" -> Quote size each side (USD) | C22: =Clip_Size -> 250000
B23: Position after being lifted on the Ask | C23: =C15-Clip_Size -> 250000
B24: Position after being hit on the Bid | C24: =C15+Clip_Size -> 750000
B25: Next fill triggers hedge? | C25: =IF(OR(ABS(C23)>Pos_Limit,ABS(C24)>Pos_Limit),"YES: a fill can breach the limit","No") -> No
B28: 3. Skew ladder: quotes at every inventory level
B29: Position (units) | C29: Utilisation | D29: Skew (ticks) | E29: Bid | F29: Ask | G29: Limit check
B30: =-6*Clip_Size -> -1500000 | C30: =B30/Pos_Limit -> -1.5 | D30: =-MAX(-1,MIN(1,C30))*Max_Skew_Ticks -> 3 | E30: =ROUND($C$8/Tick+D30-Spread_Ticks/2,0)*Tick -> 1.2795 | F30: =E30+Spread_Ticks*Tick -> 1.28 | G30: =IF(ABS(B30)>Pos_Limit,"BREACH: hedge","within limit") -> BREACH: hedge
B31: =B30+Clip_Size -> -1250000 | C31: =B31/Pos_Limit -> -1.25 | D31: =-MAX(-1,MIN(1,C31))*Max_Skew_Ticks -> 3 | E31: =ROUND($C$8/Tick+D31-Spread_Ticks/2,0)*Tick -> 1.2795 | F31: =E31+Spread_Ticks*Tick -> 1.28 | G31: =IF(ABS(B31)>Pos_Limit,"BREACH: hedge","within limit") -> BREACH: hedge
B32: =B31+Clip_Size -> -1000000 | C32: =B32/Pos_Limit -> -1 | D32: =-MAX(-1,MIN(1,C32))*Max_Skew_Ticks -> 3 | E32: =ROUND($C$8/Tick+D32-Spread_Ticks/2,0)*Tick -> 1.2795 | F32: =E32+Spread_Ticks*Tick -> 1.28 | G32: =IF(ABS(B32)>Pos_Limit,"BREACH: hedge","within limit") -> within limit
B33: =B32+Clip_Size -> -750000 | C33: =B33/Pos_Limit -> -0.75 | D33: =-MAX(-1,MIN(1,C33))*Max_Skew_Ticks -> 2.25 | E33: =ROUND($C$8/Tick+D33-Spread_Ticks/2,0)*Tick -> 1.2794 | F33: =E33+Spread_Ticks*Tick -> 1.2799 | G33: =IF(ABS(B33)>Pos_Limit,"BREACH: hedge","within limit") -> within limit
B34: =B33+Clip_Size -> -500000 | C34: =B34/Pos_Limit -> -0.5 | D34: =-MAX(-1,MIN(1,C34))*Max_Skew_Ticks -> 1.5 | E34: =ROUND($C$8/Tick+D34-Spread_Ticks/2,0)*Tick -> 1.2794 | F34: =E34+Spread_Ticks*Tick -> 1.2799 | G34: =IF(ABS(B34)>Pos_Limit,"BREACH: hedge","within limit") -> within limit
B35: =B34+Clip_Size -> -250000 | C35: =B35/Pos_Limit -> -0.25 | D35: =-MAX(-1,MIN(1,C35))*Max_Skew_Ticks -> 0.75 | E35: =ROUND($C$8/Tick+D35-Spread_Ticks/2,0)*Tick -> 1.2793 | F35: =E35+Spread_Ticks*Tick -> 1.2798 | G35: =IF(ABS(B35)>Pos_Limit,"BREACH: hedge","within limit") -> within limit
B36: =B35+Clip_Size -> 0 | C36: =B36/Pos_Limit -> 0 | D36: =-MAX(-1,MIN(1,C36))*Max_Skew_Ticks -> 0 | E36: =ROUND($C$8/Tick+D36-Spread_Ticks/2,0)*Tick -> 1.2792 | F36: =E36+Spread_Ticks*Tick -> 1.2797 | G36: =IF(ABS(B36)>Pos_Limit,"BREACH: hedge","within limit") -> within limit
B37: =B36+Clip_Size -> 250000 | C37: =B37/Pos_Limit -> 0.25 | D37: =-MAX(-1,MIN(1,C37))*Max_Skew_Ticks -> -0.75 | E37: =ROUND($C$8/Tick+D37-Spread_Ticks/2,0)*Tick -> 1.2791 | F37: =E37+Spread_Ticks*Tick -> 1.2796 | G37: =IF(ABS(B37)>Pos_Limit,"BREACH: hedge","within limit") -> within limit
B38: =B37+Clip_Size -> 500000 | C38: =B38/Pos_Limit -> 0.5 | D38: =-MAX(-1,MIN(1,C38))*Max_Skew_Ticks -> -1.5 | E38: =ROUND($C$8/Tick+D38-Spread_Ticks/2,0)*Tick -> 1.2791 | F38: =E38+Spread_Ticks*Tick -> 1.2796 | G38: =IF(ABS(B38)>Pos_Limit,"BREACH: hedge","within limit") -> within limit
B39: =B38+Clip_Size -> 750000 | C39: =B39/Pos_Limit -> 0.75 | D39: =-MAX(-1,MIN(1,C39))*Max_Skew_Ticks -> -2.25 | E39: =ROUND($C$8/Tick+D39-Spread_Ticks/2,0)*Tick -> 1.279 | F39: =E39+Spread_Ticks*Tick -> 1.2795 | G39: =IF(ABS(B39)>Pos_Limit,"BREACH: hedge","within limit") -> within limit
B40: =B39+Clip_Size -> 1000000 | C40: =B40/Pos_Limit -> 1 | D40: =-MAX(-1,MIN(1,C40))*Max_Skew_Ticks -> -3 | E40: =ROUND($C$8/Tick+D40-Spread_Ticks/2,0)*Tick -> 1.2789 | F40: =E40+Spread_Ticks*Tick -> 1.2794 | G40: =IF(ABS(B40)>Pos_Limit,"BREACH: hedge","within limit") -> within limit
B41: =B40+Clip_Size -> 1250000 | C41: =B41/Pos_Limit -> 1.25 | D41: =-MAX(-1,MIN(1,C41))*Max_Skew_Ticks -> -3 | E41: =ROUND($C$8/Tick+D41-Spread_Ticks/2,0)*Tick -> 1.2789 | F41: =E41+Spread_Ticks*Tick -> 1.2794 | G41: =IF(ABS(B41)>Pos_Limit,"BREACH: hedge","within limit") -> BREACH: hedge
B42: =B41+Clip_Size -> 1500000 | C42: =B42/Pos_Limit -> 1.5 | D42: =-MAX(-1,MIN(1,C42))*Max_Skew_Ticks -> -3 | E42: =ROUND($C$8/Tick+D42-Spread_Ticks/2,0)*Tick -> 1.2789 | F42: =E42+Spread_Ticks*Tick -> 1.2794 | G42: =IF(ABS(B42)>Pos_Limit,"BREACH: hedge","within limit") -> BREACH: hedge

Sheet Simulation
A1: ="Market-Making Simulation: "&Instrument&" ("&Inst_Type&")" -> Market-Making Simulation: USD/SGD (FX)
A2: One client RFQ per step. Edit the blue columns B:C to run your own scenario; all other cells are formulas. Position = net units bought from clients (+ long).
A3: Default scenario: market moves and client flow randomly generated by build_simulator.py (seed 277); illustrative only. Moves are in sigma units, so the same scenario runs on any instrument.
A4: Scenario input | D4: Market | G4: Exposure & skew | J4: Our quote | M4: Client trade | Q4: P&L and limit checks | U4: Back-to-back hedge | Y4: Close of step
A5: Step | B5: Market move (sigma units) | C5: Client action (BUY / SELL / NONE) | D5: Spot | E5: Fair forward | F5: Fwd points (ticks) | G5: ="Opening position ("&Unit_Label&")" -> Opening position (USD) | H5: Utilisation of limit | I5: Skew (ticks) | J5: Bid | K5: Ask | L5: Quoting status | M5: ="Client fill ("&Unit_Label&", + = we buy)" -> Client fill (USD, + = we buy) | N5: Fill price | O5: Position after client trade | P5: ="Spread capture ("&PnL_Ccy&")" -> Spread capture (SGD) | Q5: ="MTM on opening position ("&PnL_Ccy&")" -> MTM on opening position (SGD) | R5: ="Cum. P&L before hedge ("&PnL_Ccy&")" -> Cum. P&L before hedge (SGD) | S5: Position limit breach | T5: Loss limit breach | U5: Hedge trigger | V5: ="Hedge qty ("&Unit_Label&", + = we buy)" -> Hedge qty (USD, + = we buy) | W5: Hedge price | X5: ="Hedge cost ("&PnL_Ccy&")" -> Hedge cost (SGD) | Y5: ="Closing position ("&Unit_Label&")" -> Closing position (USD) | Z5: ="Step P&L ("&PnL_Ccy&")" -> Step P&L (SGD) | AA5: ="Cumulative P&L ("&PnL_Ccy&")" -> Cumulative P&L (SGD) | AB5: Quoting halted (1 = yes) | AC5: ="Closing position value ("&PnL_Ccy&")" -> Closing position value (SGD)
A6: 0 | B6: - | C6: - | D6: =Spot_Init -> 1.285 | E6: =D6*(1+Rate_B*Tenor_Days/Basis_B)/(1+Rate_A*Tenor_Days/Basis_A) -> 1.279474 | F6: =(E6-D6)/Tick -> -55.260342 | Y6: =Start_Pos -> 0 | AA6: 0 | AB6: 0 | AC6: =Y6*E6 -> 0
A7: =A6+1 -> 1 | B7: 1.8 | C7: NONE | D7: =D6+B7*Step_Vol_Ticks*Tick -> 1.28554 | E7: =D7*(1+Rate_B*Tenor_Days/Basis_B)/(1+Rate_A*Tenor_Days/Basis_A) -> 1.2800116 | F7: =(E7-D7)/Tick -> -55.283564 | G7: =Y6 -> 0 | H7: =G7/Pos_Limit -> 0 | I7: =-MAX(-1,MIN(1,H7))*Max_Skew_Ticks -> 0 | J7: =ROUND(E7/Tick+I7-Spread_Ticks/2,0)*Tick -> 1.2798 | K7: =J7+Spread_Ticks*Tick -> 1.2803 | L7: =IF(AB6=1,"HALTED","LIVE") -> LIVE | M7: =IF(L7="LIVE",IF(C7="BUY",-Clip_Size,IF(C7="SELL",Clip_Size,0)),0) -> 0 | N7: =IF(M7<0,K7,IF(M7>0,J7,0)) -> 0 | O7: =G7+M7 -> 0 | P7: =IF(M7<0,(K7-E7)*ABS(M7),IF(M7>0,(E7-J7)*M7,0)) -> 0 | Q7: =G7*(E7-E6) -> 0 | R7: =AA6+Q7+P7 -> 0 | S7: =IF(ABS(O7)>Pos_Limit,1,0) -> 0 | T7: =IF(AND(AB6=0,R7<=-Loss_Limit),1,0) -> 0 | U7: =IF(T7=1,"LOSS LIMIT",IF(S7=1,"POSITION LIMIT","")) | V7: =IF(T7=1,-O7,IF(S7=1,-(O7-SIGN(O7)*Hedge_Target),0)) -> 0 | W7: =IF(V7>0,E7+Hedge_Cost_Ticks*Tick,IF(V7<0,E7-Hedge_Cost_Ticks*Tick,0)) -> 0 | X7: =-ABS(V7)*Hedge_Cost_Ticks*Tick -> 0 | Y7: =O7+V7 -> 0 | Z7: =Q7+P7+X7 -> 0 | AA7: =AA6+Z7 -> 0 | AB7: =IF(Halt_On_Loss=1,MAX(AB6,T7),0) -> 0 | AC7: =Y7*E7 -> 0
A8: =A7+1 -> 2 | B8: -1.3 | C8: BUY | D8: =D7+B8*Step_Vol_Ticks*Tick -> 1.28515 | E8: =D8*(1+Rate_B*Tenor_Days/Basis_B)/(1+Rate_A*Tenor_Days/Basis_A) -> 1.2796233 | F8: =(E8-D8)/Tick -> -55.266793 | G8: =Y7 -> 0 | H8: =G8/Pos_Limit -> 0 | I8: =-MAX(-1,MIN(1,H8))*Max_Skew_Ticks -> 0 | J8: =ROUND(E8/Tick+I8-Spread_Ticks/2,0)*Tick -> 1.2794 | K8: =J8+Spread_Ticks*Tick -> 1.2799 | L8: =IF(AB7=1,"HALTED","LIVE") -> LIVE | M8: =IF(L8="LIVE",IF(C8="BUY",-Clip_Size,IF(C8="SELL",Clip_Size,0)),0) -> -250000 | N8: =IF(M8<0,K8,IF(M8>0,J8,0)) -> 1.2799 | O8: =G8+M8 -> -250000 | P8: =IF(M8<0,(K8-E8)*ABS(M8),IF(M8>0,(E8-J8)*M8,0)) -> 69.169819 | Q8: =G8*(E8-E7) -> 0 | R8: =AA7+Q8+P8 -> 69.169819 | S8: =IF(ABS(O8)>Pos_Limit,1,0) -> 0 | T8: =IF(AND(AB7=0,R8<=-Loss_Limit),1,0) -> 0 | U8: =IF(T8=1,"LOSS LIMIT",IF(S8=1,"POSITION LIMIT","")) | V8: =IF(T8=1,-O8,IF(S8=1,-(O8-SIGN(O8)*Hedge_Target),0)) -> 0 | W8: =IF(V8>0,E8+Hedge_Cost_Ticks*Tick,IF(V8<0,E8-Hedge_Cost_Ticks*Tick,0)) -> 0 | X8: =-ABS(V8)*Hedge_Cost_Ticks*Tick -> 0 | Y8: =O8+V8 -> -250000 | Z8: =Q8+P8+X8 -> 69.169819 | AA8: =AA7+Z8 -> 69.169819 | AB8: =IF(Halt_On_Loss=1,MAX(AB7,T8),0) -> 0 | AC8: =Y8*E8 -> -319905.83
A9: =A8+1 -> 3 | B9: -0.4 | C9: NONE | D9: =D8+B9*Step_Vol_Ticks*Tick -> 1.28503 | E9: =D9*(1+Rate_B*Tenor_Days/Basis_B)/(1+Rate_A*Tenor_Days/Basis_A) -> 1.2795038 | F9: =(E9-D9)/Tick -> -55.261632 | G9: =Y8 -> -250000 | H9: =G9/Pos_Limit -> -0.25 | I9: =-MAX(-1,MIN(1,H9))*Max_Skew_Ticks -> 0.75 | J9: =ROUND(E9/Tick+I9-Spread_Ticks/2,0)*Tick -> 1.2793 | K9: =J9+Spread_Ticks*Tick -> 1.2798 | L9: =IF(AB8=1,"HALTED","LIVE") -> LIVE | M9: =IF(L9="LIVE",IF(C9="BUY",-Clip_Size,IF(C9="SELL",Clip_Size,0)),0) -> 0 | N9: =IF(M9<0,K9,IF(M9>0,J9,0)) -> 0 | O9: =G9+M9 -> -250000 | P9: =IF(M9<0,(K9-E9)*ABS(M9),IF(M9>0,(E9-J9)*M9,0)) -> 0 | Q9: =G9*(E9-E8) -> 29.870988 | R9: =AA8+Q9+P9 -> 99.040806 | S9: =IF(ABS(O9)>Pos_Limit,1,0) -> 0 | T9: =IF(AND(AB8=0,R9<=-Loss_Limit),1,0) -> 0 | U9: =IF(T9=1,"LOSS LIMIT",IF(S9=1,"POSITION LIMIT","")) | V9: =IF(T9=1,-O9,IF(S9=1,-(O9-SIGN(O9)*Hedge_Target),0)) -> 0 | W9: =IF(V9>0,E9+Hedge_Cost_Ticks*Tick,IF(V9<0,E9-Hedge_Cost_Ticks*Tick,0)) -> 0 | X9: =-ABS(V9)*Hedge_Cost_Ticks*Tick -> 0 | Y9: =O9+V9 -> -250000 | Z9: =Q9+P9+X9 -> 29.870988 | AA9: =AA8+Z9 -> 99.040806 | AB9: =IF(Halt_On_Loss=1,MAX(AB8,T9),0) -> 0 | AC9: =Y9*E9 -> -319875.96
A10: =A9+1 -> 4 | B10: 1.2 | C10: BUY | D10: =D9+B10*Step_Vol_Ticks*Tick -> 1.28539 | E10: =D10*(1+Rate_B*Tenor_Days/Basis_B)/(1+Rate_A*Tenor_Days/Basis_A) -> 1.2798623 | F10: =(E10-D10)/Tick -> -55.277114 | G10: =Y9 -> -250000 | H10: =G10/Pos_Limit -> -0.25 | I10: =-MAX(-1,MIN(1,H10))*Max_Skew_Ticks -> 0.75 | J10: =ROUND(E10/Tick+I10-Spread_Ticks/2,0)*Tick -> 1.2797 | K10: =J10+Spread_Ticks*Tick -> 1.2802 | L10: =IF(AB9=1,"HALTED","LIVE") -> LIVE | M10: =IF(L10="LIVE",IF(C10="BUY",-Clip_Size,IF(C10="SELL",Clip_Size,0)),0) -> -250000 | N10: =IF(M10<0,K10,IF(M10>0,J10,0)) -> 1.2802 | O10: =G10+M10 -> -500000 | P10: =IF(M10<0,(K10-E10)*ABS(M10),IF(M10>0,(E10-J10)*M10,0)) -> 84.427844 | Q10: =G10*(E10-E9) -> -89.612963 | R10: =AA9+Q10+P10 -> 93.855687 | S10: =IF(ABS(O10)>Pos_Limit,1,0) -> 0 | T10: =IF(AND(AB9=0,R10<=-Loss_Limit),1,0) -> 0 | U10: =IF(T10=1,"LOSS LIMIT",IF(S10=1,"POSITION LIMIT","")) | V10: =IF(T10=1,-O10,IF(S10=1,-(O10-SIGN(O10)*Hedge_Target),0)) -> 0 | W10: =IF(V10>0,E10+Hedge_Cost_Ticks*Tick,IF(V10<0,E10-Hedge_Cost_Ticks*Tick,0)) -> 0 | X10: =-ABS(V10)*Hedge_Cost_Ticks*Tick -> 0 | Y10: =O10+V10 -> -500000 | Z10: =Q10+P10+X10 -> -5.1851189 | AA10: =AA9+Z10 -> 93.855687 | AB10: =IF(Halt_On_Loss=1,MAX(AB9,T10),0) -> 0 | AC10: =Y10*E10 -> -639931.14
A11: =A10+1 -> 5 | B11: 0.2 | C11: SELL | D11: =D10+B11*Step_Vol_Ticks*Tick -> 1.28545 | E11: =D11*(1+Rate_B*Tenor_Days/Basis_B)/(1+Rate_A*Tenor_Days/Basis_A) -> 1.279922 | F11: =(E11-D11)/Tick -> -55.279694 | G11: =Y10 -> -500000 | H11: =G11/Pos_Limit -> -0.5 | I11: =-MAX(-1,MIN(1,H11))*Max_Skew_Ticks -> 1.5 | J11: =ROUND(E11/Tick+I11-Spread_Ticks/2,0)*Tick -> 1.2798 | K11: =J11+Spread_Ticks*Tick -> 1.2803 | L11: =IF(AB10=1,"HALTED","LIVE") -> LIVE | M11: =IF(L11="LIVE",IF(C11="BUY",-Clip_Size,IF(C11="SELL",Clip_Size,0)),0) -> 250000 | N11: =IF(M11<0,K11,IF(M11>0,J11,0)) -> 1.2798 | O11: =G11+M11 -> -250000 | P11: =IF(M11<0,(K11-E11)*ABS(M11),IF(M11>0,(E11-J11)*M11,0)) -> 30.50765 | Q11: =G11*(E11-E10) -> -29.870988 | R11: =AA10+Q11+P11 -> 94.49235 | S11: =IF(ABS(O11)>Pos_Limit,1,0) -> 0 | T11: =IF(AND(AB10=0,R11<=-Loss_Limit),1,0) -> 0 | U11: =IF(T11=1,"LOSS LIMIT",IF(S11=1,"POSITION LIMIT","")) | V11: =IF(T11=1,-O11,IF(S11=1,-(O11-SIGN(O11)*Hedge_Target),0)) -> 0 | W11: =IF(V11>0,E11+Hedge_Cost_Ticks*Tick,IF(V11<0,E11-Hedge_Cost_Ticks*Tick,0)) -> 0 | X11: =-ABS(V11)*Hedge_Cost_Ticks*Tick -> 0 | Y11: =O11+V11 -> -250000 | Z11: =Q11+P11+X11 -> 0.63666258 | AA11: =AA10+Z11 -> 94.49235 | AB11: =IF(Halt_On_Loss=1,MAX(AB10,T11),0) -> 0 | AC11: =Y11*E11 -> -319980.51
A12: =A11+1 -> 6 | B12: -0.3 | C12: NONE | D12: =D11+B12*Step_Vol_Ticks*Tick -> 1.28536 | E12: =D12*(1+Rate_B*Tenor_Days/Basis_B)/(1+Rate_A*Tenor_Days/Basis_A) -> 1.2798324 | F12: =(E12-D12)/Tick -> -55.275824 | G12: =Y11 -> -250000 | H12: =G12/Pos_Limit -> -0.25 | I12: =-MAX(-1,MIN(1,H12))*Max_Skew_Ticks -> 0.75 | J12: =ROUND(E12/Tick+I12-Spread_Ticks/2,0)*Tick -> 1.2797 | K12: =J12+Spread_Ticks*Tick -> 1.2802 | L12: =IF(AB11=1,"HALTED","LIVE") -> LIVE | M12: =IF(L12="LIVE",IF(C12="BUY",-Clip_Size,IF(C12="SELL",Clip_Size,0)),0) -> 0 | N12: =IF(M12<0,K12,IF(M12>0,J12,0)) -> 0 | O12: =G12+M12 -> -250000 | P12: =IF(M12<0,(K12-E12)*ABS(M12),IF(M12>0,(E12-J12)*M12,0)) -> 0 | Q12: =G12*(E12-E11) -> 22.403241 | R12: =AA11+Q12+P12 -> 116.89559 | S12: =IF(ABS(O12)>Pos_Limit,1,0) -> 0 | T12: =IF(AND(AB11=0,R12<=-Loss_Limit),1,0) -> 0 | U12: =IF(T12=1,"LOSS LIMIT",IF(S12=1,"POSITION LIMIT","")) | V12: =IF(T12=1,-O12,IF(S12=1,-(O12-SIGN(O12)*Hedge_Target),0)) -> 0 | W12: =IF(V12>0,E12+Hedge_Cost_Ticks*Tick,IF(V12<0,E12-Hedge_Cost_Ticks*Tick,0)) -> 0 | X12: =-ABS(V12)*Hedge_Cost_Ticks*Tick -> 0 | Y12: =O12+V12 -> -250000 | Z12: =Q12+P12+X12 -> 22.403241 | AA12: =AA11+Z12 -> 116.89559 | AB12: =IF(Halt_On_Loss=1,MAX(AB11,T12),0) -> 0 | AC12: =Y12*E12 -> -319958.1
A13: =A12+1 -> 7 | B13: -0.7 | C13: SELL | D13: =D12+B13*Step_Vol_Ticks*Tick -> 1.28515 | E13: =D13*(1+Rate_B*Tenor_Days/Basis_B)/(1+Rate_A*Tenor_Days/Basis_A) -> 1.2796233 | F13: =(E13-D13)/Tick -> -55.266793 | G13: =Y12 -> -250000 | H13: =G13/Pos_Limit -> -0.25 | I13: =-MAX(-1,MIN(1,H13))*Max_Skew_Ticks -> 0.75 | J13: =ROUND(E13/Tick+I13-Spread_Ticks/2,0)*Tick -> 1.2794 | K13: =J13+Spread_Ticks*Tick -> 1.2799 | L13: =IF(AB12=1,"HALTED","LIVE") -> LIVE | M13: =IF(L13="LIVE",IF(C13="BUY",-Clip_Size,IF(C13="SELL",Clip_Size,0)),0) -> 250000 | N13: =IF(M13<0,K13,IF(M13>0,J13,0)) -> 1.2794 | O13: =G13+M13 -> 0 | P13: =IF(M13<0,(K13-E13)*ABS(M13),IF(M13>0,(E13-J13)*M13,0)) -> 55.830181 | Q13: =G13*(E13-E12) -> 52.274228 | R13: =AA12+Q13+P13 -> 225 | S13: =IF(ABS(O13)>Pos_Limit,1,0) -> 0 | T13: =IF(AND(AB12=0,R13<=-Loss_Limit),1,0) -> 0 | U13: =IF(T13=1,"LOSS LIMIT",IF(S13=1,"POSITION LIMIT","")) | V13: =IF(T13=1,-O13,IF(S13=1,-(O13-SIGN(O13)*Hedge_Target),0)) -> 0 | W13: =IF(V13>0,E13+Hedge_Cost_Ticks*Tick,IF(V13<0,E13-Hedge_Cost_Ticks*Tick,0)) -> 0 | X13: =-ABS(V13)*Hedge_Cost_Ticks*Tick -> 0 | Y13: =O13+V13 -> 0 | Z13: =Q13+P13+X13 -> 108.10441 | AA13: =AA12+Z13 -> 225 | AB13: =IF(Halt_On_Loss=1,MAX(AB12,T13),0) -> 0 | AC13: =Y13*E13 -> 0
A14: =A13+1 -> 8 | B14: 0 | C14: BUY | D14: =D13+B14*Step_Vol_Ticks*Tick -> 1.28515 | E14: =D14*(1+Rate_B*Tenor_Days/Basis_B)/(1+Rate_A*Tenor_Days/Basis_A) -> 1.2796233 | F14: =(E14-D14)/Tick -> -55.266793 | G14: =Y13 -> 0 | H14: =G14/Pos_Limit -> 0 | I14: =-MAX(-1,MIN(1,H14))*Max_Skew_Ticks -> 0 | J14: =ROUND(E14/Tick+I14-Spread_Ticks/2,0)*Tick -> 1.2794 | K14: =J14+Spread_Ticks*Tick -> 1.2799 | L14: =IF(AB13=1,"HALTED","LIVE") -> LIVE | M14: =IF(L14="LIVE",IF(C14="BUY",-Clip_Size,IF(C14="SELL",Clip_Size,0)),0) -> -250000 | N14: =IF(M14<0,K14,IF(M14>0,J14,0)) -> 1.2799 | O14: =G14+M14 -> -250000 | P14: =IF(M14<0,(K14-E14)*ABS(M14),IF(M14>0,(E14-J14)*M14,0)) -> 69.169819 | Q14: =G14*(E14-E13) -> 0 | R14: =AA13+Q14+P14 -> 294.16982 | S14: =IF(ABS(O14)>Pos_Limit,1,0) -> 0 | T14: =IF(AND(AB13=0,R14<=-Loss_Limit),1,0) -> 0 | U14: =IF(T14=1,"LOSS LIMIT",IF(S14=1,"POSITION LIMIT","")) | V14: =IF(T14=1,-O14,IF(S14=1,-(O14-SIGN(O14)*Hedge_Target),0)) -> 0 | W14: =IF(V14>0,E14+Hedge_Cost_Ticks*Tick,IF(V14<0,E14-Hedge_Cost_Ticks*Tick,0)) -> 0 | X14: =-ABS(V14)*Hedge_Cost_Ticks*Tick -> 0 | Y14: =O14+V14 -> -250000 | Z14: =Q14+P14+X14 -> 69.169819 | AA14: =AA13+Z14 -> 294.16982 | AB14: =IF(Halt_On_Loss=1,MAX(AB13,T14),0) -> 0 | AC14: =Y14*E14 -> -319905.83
A15: =A14+1 -> 9 | B15: 1 | C15: SELL | D15: =D14+B15*Step_Vol_Ticks*Tick -> 1.28545 | E15: =D15*(1+Rate_B*Tenor_Days/Basis_B)/(1+Rate_A*Tenor_Days/Basis_A) -> 1.279922 | F15: =(E15-D15)/Tick -> -55.279694 | G15: =Y14 -> -250000 | H15: =G15/Pos_Limit -> -0.25 | I15: =-MAX(-1,MIN(1,H15))*Max_Skew_Ticks -> 0.75 | J15: =ROUND(E15/Tick+I15-Spread_Ticks/2,0)*Tick -> 1.2797 | K15: =J15+Spread_Ticks*Tick -> 1.2802 | L15: =IF(AB14=1,"HALTED","LIVE") -> LIVE | M15: =IF(L15="LIVE",IF(C15="BUY",-Clip_Size,IF(C15="SELL",Clip_Size,0)),0) -> 250000 | N15: =IF(M15<0,K15,IF(M15>0,J15,0)) -> 1.2797 | O15: =G15+M15 -> 0 | P15: =IF(M15<0,(K15-E15)*ABS(M15),IF(M15>0,(E15-J15)*M15,0)) -> 55.50765 | Q15: =G15*(E15-E14) -> -74.677469 | R15: =AA14+Q15+P15 -> 275 | S15: =IF(ABS(O15)>Pos_Limit,1,0) -> 0 | T15: =IF(AND(AB14=0,R15<=-Loss_Limit),1,0) -> 0 | U15: =IF(T15=1,"LOSS LIMIT",IF(S15=1,"POSITION LIMIT","")) | V15: =IF(T15=1,-O15,IF(S15=1,-(O15-SIGN(O15)*Hedge_Target),0)) -> 0 | W15: =IF(V15>0,E15+Hedge_Cost_Ticks*Tick,IF(V15<0,E15-Hedge_Cost_Ticks*Tick,0)) -> 0 | X15: =-ABS(V15)*Hedge_Cost_Ticks*Tick -> 0 | Y15: =O15+V15 -> 0 | Z15: =Q15+P15+X15 -> -19.169819 | AA15: =AA14+Z15 -> 275 | AB15: =IF(Halt_On_Loss=1,MAX(AB14,T15),0) -> 0 | AC15: =Y15*E15 -> 0
A16: =A15+1 -> 10 | B16: 0.4 | C16: NONE | D16: =D15+B16*Step_Vol_Ticks*Tick -> 1.28557 | E16: =D16*(1+Rate_B*Tenor_Days/Basis_B)/(1+Rate_A*Tenor_Days/Basis_A) -> 1.2800415 | F16: =(E16-D16)/Tick -> -55.284854 | G16: =Y15 -> 0 | H16: =G16/Pos_Limit -> 0 | I16: =-MAX(-1,MIN(1,H16))*Max_Skew_Ticks -> 0 | J16: =ROUND(E16/Tick+I16-Spread_Ticks/2,0)*Tick -> 1.2798 | K16: =J16+Spread_Ticks*Tick -> 1.2803 | L16: =IF(AB15=1,"HALTED","LIVE") -> LIVE | M16: =IF(L16="LIVE",IF(C16="BUY",-Clip_Size,IF(C16="SELL",Clip_Size,0)),0) -> 0 | N16: =IF(M16<0,K16,IF(M16>0,J16,0)) -> 0 | O16: =G16+M16 -> 0 | P16: =IF(M16<0,(K16-E16)*ABS(M16),IF(M16>0,(E16-J16)*M16,0)) -> 0 | Q16: =G16*(E16-E15) -> 0 | R16: =AA15+Q16+P16 -> 275 | S16: =IF(ABS(O16)>Pos_Limit,1,0) -> 0 | T16: =IF(AND(AB15=0,R16<=-Loss_Limit),1,0) -> 0 | U16: =IF(T16=1,"LOSS LIMIT",IF(S16=1,"POSITION LIMIT","")) | V16: =IF(T16=1,-O16,IF(S16=1,-(O16-SIGN(O16)*Hedge_Target),0)) -> 0 | W16: =IF(V16>0,E16+Hedge_Cost_Ticks*Tick,IF(V16<0,E16-Hedge_Cost_Ticks*Tick,0)) -> 0 | X16: =-ABS(V16)*Hedge_Cost_Ticks*Tick -> 0 | Y16: =O16+V16 -> 0 | Z16: =Q16+P16+X16 -> 0 | AA16: =AA15+Z16 -> 275 | AB16: =IF(Halt_On_Loss=1,MAX(AB15,T16),0) -> 0 | AC16: =Y16*E16 -> 0
A17: =A16+1 -> 11 | B17: 0.2 | C17: NONE | D17: =D16+B17*Step_Vol_Ticks*Tick -> 1.28563 | E17: =D17*(1+Rate_B*Tenor_Days/Basis_B)/(1+Rate_A*Tenor_Days/Basis_A) -> 1.2801013 | F17: =(E17-D17)/Tick -> -55.287435 | G17: =Y16 -> 0 | H17: =G17/Pos_Limit -> 0 | I17: =-MAX(-1,MIN(1,H17))*Max_Skew_Ticks -> 0 | J17: =ROUND(E17/Tick+I17-Spread_Ticks/2,0)*Tick -> 1.2799 | K17: =J17+Spread_Ticks*Tick -> 1.2804 | L17: =IF(AB16=1,"HALTED","LIVE") -> LIVE | M17: =IF(L17="LIVE",IF(C17="BUY",-Clip_Size,IF(C17="SELL",Clip_Size,0)),0) -> 0 | N17: =IF(M17<0,K17,IF(M17>0,J17,0)) -> 0 | O17: =G17+M17 -> 0 | P17: =IF(M17<0,(K17-E17)*ABS(M17),IF(M17>0,(E17-J17)*M17,0)) -> 0 | Q17: =G17*(E17-E16) -> 0 | R17: =AA16+Q17+P17 -> 275 | S17: =IF(ABS(O17)>Pos_Limit,1,0) -> 0 | T17: =IF(AND(AB16=0,R17<=-Loss_Limit),1,0) -> 0 | U17: =IF(T17=1,"LOSS LIMIT",IF(S17=1,"POSITION LIMIT","")) | V17: =IF(T17=1,-O17,IF(S17=1,-(O17-SIGN(O17)*Hedge_Target),0)) -> 0 | W17: =IF(V17>0,E17+Hedge_Cost_Ticks*Tick,IF(V17<0,E17-Hedge_Cost_Ticks*Tick,0)) -> 0 | X17: =-ABS(V17)*Hedge_Cost_Ticks*Tick -> 0 | Y17: =O17+V17 -> 0 | Z17: =Q17+P17+X17 -> 0 | AA17: =AA16+Z17 -> 275 | AB17: =IF(Halt_On_Loss=1,MAX(AB16,T17),0) -> 0 | AC17: =Y17*E17 -> 0
A18: =A17+1 -> 12 | B18: 0.3 | C18: NONE | D18: =D17+B18*Step_Vol_Ticks*Tick -> 1.28572 | E18: =D18*(1+Rate_B*Tenor_Days/Basis_B)/(1+Rate_A*Tenor_Days/Basis_A) -> 1.2801909 | F18: =(E18-D18)/Tick -> -55.291305 | G18: =Y17 -> 0 | H18: =G18/Pos_Limit -> 0 | I18: =-MAX(-1,MIN(1,H18))*Max_Skew_Ticks -> 0 | J18: =ROUND(E18/Tick+I18-Spread_Ticks/2,0)*Tick -> 1.2799 | K18: =J18+Spread_Ticks*Tick -> 1.2804 | L18: =IF(AB17=1,"HALTED","LIVE") -> LIVE | M18: =IF(L18="LIVE",IF(C18="BUY",-Clip_Size,IF(C18="SELL",Clip_Size,0)),0) -> 0 | N18: =IF(M18<0,K18,IF(M18>0,J18,0)) -> 0 | O18: =G18+M18 -> 0 | P18: =IF(M18<0,(K18-E18)*ABS(M18),IF(M18>0,(E18-J18)*M18,0)) -> 0 | Q18: =G18*(E18-E17) -> 0 | R18: =AA17+Q18+P18 -> 275 | S18: =IF(ABS(O18)>Pos_Limit,1,0) -> 0 | T18: =IF(AND(AB17=0,R18<=-Loss_Limit),1,0) -> 0 | U18: =IF(T18=1,"LOSS LIMIT",IF(S18=1,"POSITION LIMIT","")) | V18: =IF(T18=1,-O18,IF(S18=1,-(O18-SIGN(O18)*Hedge_Target),0)) -> 0 | W18: =IF(V18>0,E18+Hedge_Cost_Ticks*Tick,IF(V18<0,E18-Hedge_Cost_Ticks*Tick,0)) -> 0 | X18: =-ABS(V18)*Hedge_Cost_Ticks*Tick -> 0 | Y18: =O18+V18 -> 0 | Z18: =Q18+P18+X18 -> 0 | AA18: =AA17+Z18 -> 275 | AB18: =IF(Halt_On_Loss=1,MAX(AB17,T18),0) -> 0 | AC18: =Y18*E18 -> 0
... A66: =A65+1 -> 60 | B66: -0.5 | C66: SELL | D66: =D65+B66*Step_Vol_Ticks*Tick -> 1.27756 | E66: =D66*(1+Rate_B*Tenor_Days/Basis_B)/(1+Rate_A*Tenor_Days/Basis_A) -> 1.272066 | F66: =(E66-D66)/Tick -> -54.940391 | G66: =Y65 -> 0 | H66: =G66/Pos_Limit -> 0 | I66: =-MAX(-1,MIN(1,H66))*Max_Skew_Ticks -> 0 | J66: =ROUND(E66/Tick+I66-Spread_Ticks/2,0)*Tick -> 1.2718 | K66: =J66+Spread_Ticks*Tick -> 1.2723 | L66: =IF(AB65=1,"HALTED","LIVE") -> HALTED | M66: =IF(L66="LIVE",IF(C66="BUY",-Clip_Size,IF(C66="SELL",Clip_Size,0)),0) -> 0 | N66: =IF(M66<0,K66,IF(M66>0,J66,0)) -> 0 | O66: =G66+M66 -> 0 | P66: =IF(M66<0,(K66-E66)*ABS(M66),IF(M66>0,(E66-J66)*M66,0)) -> 0 | Q66: =G66*(E66-E65) -> 0 | R66: =AA65+Q66+P66 -> -1928.1271 | S66: =IF(ABS(O66)>Pos_Limit,1,0) -> 0 | T66: =IF(AND(AB65=0,R66<=-Loss_Limit),1,0) -> 0 | U66: =IF(T66=1,"LOSS LIMIT",IF(S66=1,"POSITION LIMIT","")) | V66: =IF(T66=1,-O66,IF(S66=1,-(O66-SIGN(O66)*Hedge_Target),0)) -> 0 | W66: =IF(V66>0,E66+Hedge_Cost_Ticks*Tick,IF(V66<0,E66-Hedge_Cost_Ticks*Tick,0)) -> 0 | X66: =-ABS(V66)*Hedge_Cost_Ticks*Tick -> 0 | Y66: =O66+V66 -> 0 | Z66: =Q66+P66+X66 -> 0 | AA66: =AA65+Z66 -> -1928.1271 | AB66: =IF(Halt_On_Loss=1,MAX(AB65,T66),0) -> 1 | AC66: =Y66*E66 -> 0

Sheet Summary
B1: ="Simulation Summary: "&Instrument -> Simulation Summary: USD/SGD
B2: All figures are live formulas over the Simulation sheet.
B4: ACTIVITY
B5: Steps simulated | C5: =COUNT(Simulation!$A$7:$A$66) -> 60
B6: Client fills | C6: =COUNTIF(Simulation!$M$7:$M$66,"<>0") -> 26 | D6: RFQs that traded (quoting live)
B7: Client bought (we sold at Ask) | C7: =COUNTIF(Simulation!$M$7:$M$66,"<0") -> 6
B8: Client sold (we bought at Bid) | C8: =COUNTIF(Simulation!$M$7:$M$66,">0") -> 20
B9: ="Client volume traded ("&Unit_Label&")" -> Client volume traded (USD) | C9: =SUMPRODUCT(ABS(Simulation!$M$7:$M$66)) -> 6500000
B10: Position-limit hedges | C10: =SUMPRODUCT((Simulation!$S$7:$S$66=1)*(Simulation!$T$7:$T$66=0)) -> 2 | D10: Hedged back to the residual level
B11: Loss-limit flattenings | C11: =SUM(Simulation!$T$7:$T$66) -> 1
B12: ="Hedge volume traded with street ("&Unit_Label&")" -> Hedge volume traded with street (USD) | C12: =SUMPRODUCT(ABS(Simulation!$V$7:$V$66)) -> 3500000
B14: RISK USAGE
B15: ="Largest |position| after client fill ("&Unit_Label&")" -> Largest |position| after client fill (USD) | C15: =MAX(MAX(Simulation!$O$7:$O$66),-MIN(Simulation!$O$7:$O$66)) -> 1250000 | D15: Before any hedge
B16: ="Largest |closing position| ("&Unit_Label&")" -> Largest |closing position| (USD) | C16: =MAX(MAX(Simulation!$Y$7:$Y$66),-MIN(Simulation!$Y$7:$Y$66)) -> 1000000 | D16: After hedging
B17: ="Position limit ("&Unit_Label&")" -> Position limit (USD) | C17: =Pos_Limit -> 1000000
B18: ="Worst cumulative P&L ("&PnL_Ccy&")" -> Worst cumulative P&L (SGD) | C18: =MIN(Simulation!$AA$6:$AA$66) -> -1928.1271
B19: Loss limit used at worst point | C19: =MAX(0,-C18)/Loss_Limit -> 1.0711817 | D19: 100% = limit breached
B20: Quoting halted at end of run? | C20: =IF(Simulation!$AB$66=1,"YES","NO") -> YES
B21: Step at which loss limit hit | C21: =IFERROR(INDEX(Simulation!$A$7:$A$66,MATCH(1,Simulation!$T$7:$T$66,0)),"n/a") -> 42
B23: ="P&L ATTRIBUTION ("&PnL_Ccy&")" -> P&L ATTRIBUTION (SGD)
B24: Spread capture vs fair forward | C24: =SUM(Simulation!$P$7:$P$66) -> 2073.6011
B25: Mark-to-market on inventory | C25: =SUM(Simulation!$Q$7:$Q$66) -> -3651.7282 | D25: Opening position x change in fair forward
B26: Hedge execution cost | C26: =SUM(Simulation!$X$7:$X$66) -> -350
B27: Total P&L | C27: =SUM(C24:C26) -> -1928.1271
B28: Closing cumulative P&L | C28: =Simulation!$AA$66 -> -1928.1271
B30: INTEGRITY CHECKS
B31: P&L attribution reconciles | C31: =IF(ABS(C27-C28)<0.005,"OK","ERROR") -> OK | D31: Components sum to cumulative P&L
B32: Position roll-forward reconciles | C32: =IF(ABS(Start_Pos+SUM(Simulation!$M$7:$M$66)+SUM(Simulation!$V$7:$V$66)-Simulation!$Y$66)<0.5,"OK","ERROR") -> OK | D32: Start + client fills + hedges = closing position
B33: Hedge respects limit | C33: =IF(SUMPRODUCT((Simulation!$Y$7:$Y$66<>0)*(ABS(Simulation!$Y$7:$Y$66)>Pos_Limit))=0,"OK","ERROR") -> OK | D33: No step ends outside the position limit
